[
  {
    "code": "contract BEP20 {\n}",
    "startLine": 1,
    "endLine": 2,
    "event": "add"
  },
  {
    "code": "mapping (address=>uint256) balances;",
    "startLine": 2,
    "endLine": 2,
    "event": "add"
  },
  {
    "code": "\n",
    "startLine": 3,
    "endLine": 3,
    "event": "add"
  },
  {
    "code": "uint256 public totalSupply;",
    "startLine": 4,
    "endLine": 4,
    "event": "add"
  },
  {
    "code": "\n",
    "startLine": 5,
    "endLine": 5,
    "event": "add"
  },
  {
    "code": "mapping (address=>mapping (address=>uint256)) allowed;",
    "startLine": 6,
    "endLine": 6,
    "event": "add"
  },
  {
    "code": "\n",
    "startLine": 7,
    "endLine": 7,
    "event": "add"
  },
  {
    "code": "function transferFrom(address _from,address _to,uint256 _amount) public returns (bool success) {\n}",
    "startLine": 8,
    "endLine": 9,
    "event": "add"
  },
  {
    "code": "require (balances[_from]>=_amount&&allowed[_from][msg.sender]>=_amount&&_amount>0&&balances[_to]+_amount>balances[_to]);",
    "startLine": 9,
    "endLine": 9,
    "event": "add"
  },
  {
    "code": "balances[_from]-=_amount;",
    "startLine": 10,
    "endLine": 10,
    "event": "add"
  },
  {
    "code": "allowed[_from][msg.sender]-=_amount;",
    "startLine": 11,
    "endLine": 11,
    "event": "add"
  },
  {
    "code": "balances[_to]+=_amount;",
    "startLine": 12,
    "endLine": 12,
    "event": "add"
  },
  {
    "code": "return true;",
    "startLine": 13,
    "endLine": 13,
    "event": "add"
  }
]